[
	{
		"name": "iLoveIMG",
		"url": "https://www.iloveimg.com/zh-cn",
		"logo": "/images/share/7e91e93e3cdd586b.svg",
		"description": "免费图片处理网站，我经常用来压缩图片，压缩效果会比 Tinypng 更好。链式处理功能非常好用。",
		"tags": [
			"图片"
		],
		"stars": 4
	},
	{
		"name": "TinyPNG",
		"url": "https://tinypng.com/",
		"logo": "https://tinypng.com/static/images/george-anim/large_george_x2.webp",
		"description": "国际上比较出名的压缩图片工具，过去的书本中知晓的这个网站，但是有图片大小限制，也有数量限制。挺好的压缩图片替代品。",
		"tags": [
			"图片"
		],
		"stars": 3
	},
	{
		"name": "removebg",
		"url": "https://www.remove.bg/zh",
		"logo": "/images/share/859bfb2ef1c6a503.svg",
		"description": "AI 抠图工具，特点是界面简洁，效果比 windows 自带的去除背景会更好一些，缺点是有免费有导出大小限制",
		"tags": [
			"图片",
			"AI"
		],
		"stars": 3
	},
	{
		"name": "Webp 转换压缩",
		"logo": "https://www.yysuni.com/images/avatar.png",
		"url": "https://www.yysuni.com/image-toolbox",
		"description": "无限压缩，快且方便，可以直接对比效果",
		"tags": [
			"图片"
		],
		"stars": 3
	},
	{
		"name": "Awesome Robotic Tooling",
		"logo": "https://avatars.githubusercontent.com/u/6413976?v=4",
		"url": "https://github.com/Ly0n/awesome-robotic-tooling",
		"description": "一份精选的工具列表，用于使用 C++ 和 Python 进行专业机器人开发，并涵盖 ROS、自动驾驶和航空航天等领域。\n为了避免重复发明轮子，你需要了解轮子本身。这份清单旨在展示软件和硬件开发领域中各种开源免费工具，这些工具在专业机器人开发中非常实用。",
		"tags": [
			"开源项目",
			"机器人"
		],
		"stars": 4
	},
	{
		"name": "MoneyPrinter V2",
		"logo": "https://avatars.githubusercontent.com/u/78088687?v=4",
		"url": "https://github.com/FujiwaraChoki/MoneyPrinterV2?tab=readme-ov-file",
		"description": "一款能够自动完成在线赚钱流程的应用程序。MPV2（MoneyPrinter Version 2）顾名思义，是MoneyPrinter项目的第二个版本。它完全重写了原项目，专注于更广泛的功能和更模块化的架构。",
		"tags": [
			"开源项目",
			"赚钱工具"
		],
		"stars": 4
	},
	{
		"name": "PythonRobotics",
		"logo": "https://atsushisakai.github.io/PythonRobotics/_static/icon.png",
		"url": "https://atsushisakai.github.io/PythonRobotics/index.html",
		"description": "这是一个开源软件（OSS）项目：PythonRobotics，它是一套包含机器人算法的Python代码集。",
		"tags": [
			"机器人"
		],
		"stars": 4
	}
]